wRip/Config.py
wRip/__init__.py
wRip/app.py
wRip/setupDir.py
wrip-0.0.2.dist-info/METADATA
wrip-0.0.2.dist-info/WHEEL
wrip-0.0.2.dist-info/top_level.txt
wrip-0.0.2.dist-info/RECORD
