Metadata-Version: 2.1
Name: wrip
Version: 0.0.2
Summary: All-in-one Archiver solution
Home-page: UNKNOWN
Author: Zachary
License: UNKNOWN
Platform: UNKNOWN
Classifier: Programming Language :: Python :: 3
Classifier: License :: OSI Approved :: MIT License
Classifier: Operating System :: OS Independent
